README.txt
setup.cfg
setup.py
Products/__init__.py
Products.SingleKeywordWidget.egg-info/PKG-INFO
Products.SingleKeywordWidget.egg-info/SOURCES.txt
Products.SingleKeywordWidget.egg-info/dependency_links.txt
Products.SingleKeywordWidget.egg-info/entry_points.txt
Products.SingleKeywordWidget.egg-info/namespace_packages.txt
Products.SingleKeywordWidget.egg-info/not-zip-safe
Products.SingleKeywordWidget.egg-info/requires.txt
Products.SingleKeywordWidget.egg-info/top_level.txt
Products/SingleKeywordWidget/__init__.py
Products/SingleKeywordWidget/configure.zcml
Products/SingleKeywordWidget/widget.py
Products/SingleKeywordWidget/profiles/default/metadata.xml
Products/SingleKeywordWidget/profiles/default/skins.xml
Products/SingleKeywordWidget/skins/singlekeywordwidget/singlekeyword.pt
docs/HISTORY.txt