Metadata-Version: 1.0
Name: Products.SingleKeywordWidget
Version: 1.0a1
Summary: UNKNOWN
Home-page: http://raptus.com
Author: Raptus AG
Author-email: skaeser@raptus.com
License: GPL
Keywords: plone archetypes widget
Platform: UNKNOWN
Classifier: Programming Language :: Python
Classifier: Topic :: Software Development :: Libraries :: Python Modules
